[1,["20g1ukYUVPvKWKBRznAKo+@f9941","54TknWPwVPqJqeCR+Y/Czo@f9941","95EkngnxZFbYuFpsqVTaFr@f9941","21HjY3bOdA7Ka+nIZXuhNe","fdoJXLgx1GAa2UhGATlj3o","0e1QA89JNM6ZgvTPgXGrEp@6c48a","18wyS2/ZhDwqBAdN0jeUSO@6c48a","20g1ukYUVPvKWKBRznAKo+@6c48a","32AkTFaANBp5L8SnSVs5y4@6c48a","48POndufFDK7BNQ26XQorI@6c48a","54TknWPwVPqJqeCR+Y/Czo@6c48a","8eZAvtMDlDzIVQjSpyHZwo@6c48a","95EkngnxZFbYuFpsqVTaFr@6c48a","99Za6Uj2lH0aXljVMWJBYo@6c48a","afqpGvUo1Kc7ZqPp9OhzBE@6c48a","dcQnQpurhPV5QS0VIK638A@6c48a","79zU9tAdJCkJoqIX4CjnzU","8eZAvtMDlDzIVQjSpyHZwo@f9941","dcQnQpurhPV5QS0VIK638A@f9941","18wyS2/ZhDwqBAdN0jeUSO@f9941","0e1QA89JNM6ZgvTPgXGrEp@f9941","32AkTFaANBp5L8SnSVs5y4@f9941","48POndufFDK7BNQ26XQorI@f9941","99Za6Uj2lH0aXljVMWJBYo@f9941","afqpGvUo1Kc7ZqPp9OhzBE@f9941","54zGAYtFhL1Jeg1gtbIMPa","9fW50XyA9G64TEjziz0bkB","5bUrf88btGuKMPxE/JgJQT"],["node","_target","_normalSprite","_hoverSprite","_pressedSprite","_disabledSprite","_font","_textureSource","_spriteFrame","_customMaterial","_parent","_cameraComponent","windowContent","options","mainOption","spawner","scene","pointsLabel","populationBoard","wbcLabel","rbcLabel","virusLabel","_tmxFile","virusPrefab","RBCPrefab","WBCPrefab"],["cc.SpriteFrame",["cc.Node",["_name","_layer","_objFlags","_id","_components","_parent","_lpos","_children"],-1,9,1,5,2],["cc.Label",["_actualFontSize","_horizontalAlign","_fontSize","_isSystemFontUsed","_string","_overflow","_enableWrapText","_underlineHeight","_cacheMode","node","_color","_customMaterial","_font"],-6,1,5,6,6],["cc.Node",["_name","_layer","_objFlags","_components","_lpos","_parent","_children"],0,12,5,1,2],["cc.Sprite",["_sizeMode","_type","node","_customMaterial","_spriteFrame"],1,1,6,6],["cc.Button",["_transition","node","_target","clickEvents","_normalColor","_hoverColor","_pressedColor","_normalSprite","_hoverSprite","_pressedSprite","_disabledSprite","_disabledColor"],2,1,1,9,5,5,5,6,6,6,6,5],["cc.UITransform",["node","_contentSize","_anchorPoint"],3,1,5,5],["cc.ClickEvent",["_componentId","handler","customEventData","target"],0,1],["cc.TTFFont",["_name","_native"],1],["cc.SceneAsset",["_name"],2],["cc.Canvas",["node","_cameraComponent"],3,1,1],["cc.Widget",["_alignFlags","node"],2,1],["cc.UIOpacity",["node"],3,1],["ff3228rtPpJRYYqQzVqs25b",["node"],3,1],["4de6e3gLBhEEJi/mQFx37BW",["node","mainOption","options","windowContent"],3,1,1,1,1],["cc.TiledMap",["node","_tmxFile"],3,1,6],["d94cb2e+wNP8qYF2gpMIrOo",[],3],["cc.Scene",["_name","_children","_prefab","_globals"],2,2,4,4],["cc.PrefabInfo",["root","asset","fileId","instance","targetOverrides","nestedPrefabInstanceRoots"],-3],["cc.SceneGlobals",["ambient","shadows","_skybox","fog","octree","skin","lightProbeInfo","postSettings"],3,4,4,4,4,4,4,4,4],["cc.AmbientInfo",["_skyIllumLDR","_skyColorHDR","_skyColorLDR"],2,5,5],["cc.ShadowsInfo",["_size"],3,5],["cc.SkyboxInfo",[],3],["cc.FogInfo",["_fogColor"],3,5],["cc.OctreeInfo",[],3],["cc.SkinInfo",[],3],["cc.LightProbeInfo",[],3],["cc.PostSettingsInfo",[],3],["cc.TiledLayer",["node"],3,1],["59212C5D3pC77C/KSWMdbLM",["node","spawner"],3,1,1],["cc.Camera",["_projection","_priority","_fov","_orthoHeight","_far","_visibility","node","_color"],-3,1,5],["e1d48uE7jtHQpbucvyrJ7nN",["node","healthLabel","speedLabel","strengthLabel","resistanceLabel","reproductionRateLabel","points"],3,1,1,1,1,1,1,1],["cc9a2OcZ7BH4oet9K5jsA5d",["node","healthLabel","speedLabel","resistanceLabel","reproductionRateLabel","points"],3,1,1,1,1,1,1],["6da4fGUOd5IzZ8j4KlDjm2X",["node","healthLabel","speedLabel","strengthLabel","resistanceLabel","reproductionRateLabel","points"],3,1,1,1,1,1,1,1],["69089FN9RNLz7pB4j0Iuhpc",["node","virusManager","wbcManager","rbcManager"],3,1,1,1,1],["ff03cM9pSdH05rFZNBmPPiu",["node","virusManager","rbcManager","wbcManager"],3,1,1,1,1],["f3f761CSpJPobhDdZNlQj0g",["node"],3,1]],[[6,0,1,1],[1,0,1,5,7,4,6,3],[6,0,1,2,1],[1,0,1,5,4,3],[5,0,1,3,4,2,7,8,9,10,2],[7,0,1,2,3,4],[2,4,0,2,5,6,9,10,6],[3,0,1,5,3,4,3],[6,0,1],[2,1,0,2,3,9,5],[12,0,1],[1,0,1,5,7,4,3],[1,0,1,5,4,6,3],[4,0,2,3,4,2],[4,0,2,4,2],[7,0,1,3,3],[3,0,1,6,3,4,3],[3,0,1,5,6,3,4,3],[2,4,1,0,3,9,10,5],[4,1,0,2,3],[5,1,3,5,6,2,1],[5,0,1,4,2,2],[2,4,1,0,2,5,6,3,7,8,9,10,11,12,10],[8,0,1,3],[9,0,2],[3,0,2,1,5,3,4,4],[3,0,1,5,3,3],[1,0,1,3,7,4,6,4],[1,0,2,1,5,4,6,4],[1,0,2,1,5,7,4,4],[1,0,2,1,5,4,4],[1,0,3,5,4,6,3],[10,0,1,1],[11,0,1,2],[4,0,2,3,2],[13,0,1],[14,0,1,2,3,1],[5,0,1,3,4,5,6,11,2,7,8,9,10,2],[15,0,1,1],[16,1],[2,1,0,2,3,9,10,5],[2,4,1,0,2,3,9,10,6],[17,0,1,2,3,2],[18,0,1,2,3,4,5,7],[19,0,1,2,3,4,5,6,7,1],[20,0,1,2,2],[21,0,1],[22,1],[23,0,1],[24,1],[25,1],[26,1],[27,1],[28,0,1],[29,0,1,1],[30,0,1,2,3,4,5,6,7,7],[31,0,1,2,3,4,5,6,1],[32,0,1,2,3,4,5,1],[33,0,1,2,3,4,5,6,1],[34,0,1,2,3,1],[35,0,1,2,3,1],[36,0,1]],[[[{"name":"window","rect":{"x":135,"y":5,"width":755,"height":485},"offset":{"x":12.5,"y":2.5},"originalSize":{"width":1000,"height":500},"rotated":false,"capInsets":[0,0,0,0],"vertices":{"rawPosition":[-377.5,-242.5,0,377.5,-242.5,0,-377.5,242.5,0,377.5,242.5,0],"indexes":[0,1,2,2,1,3],"uv":[135,495,890,495,135,10,890,10],"nuv":[0.135,0.02,0.89,0.02,0.135,0.99,0.89,0.99],"minPos":{"x":-377.5,"y":-242.5,"z":0},"maxPos":{"x":377.5,"y":242.5,"z":0}},"packable":true,"pixelsToUnit":100,"pivot":{"x":0.5,"y":0.5},"meshType":0}],[0],0,[0],[7],[5]],[[{"name":"choice","rect":{"x":310,"y":135,"width":665,"height":60},"offset":{"x":142.5,"y":85},"originalSize":{"width":1000,"height":500},"rotated":false,"capInsets":[0,0,0,0],"vertices":{"rawPosition":[-332.5,-30,0,332.5,-30,0,-332.5,30,0,332.5,30,0],"indexes":[0,1,2,2,1,3],"uv":[310,365,975,365,310,305,975,305],"nuv":[0.31,0.61,0.975,0.61,0.31,0.73,0.975,0.73],"minPos":{"x":-332.5,"y":-30,"z":0},"maxPos":{"x":332.5,"y":30,"z":0}},"packable":true,"pixelsToUnit":100,"pivot":{"x":0.5,"y":0.5},"meshType":0}],[0],0,[0],[7],[6]],[[{"name":"default_btn_normal","rect":{"x":0,"y":0,"width":40,"height":40},"offset":{"x":0,"y":0},"originalSize":{"width":40,"height":40},"rotated":false,"capInsets":[12,12,12,12],"vertices":{"rawPosition":[-20,-20,0,20,-20,0,-20,20,0,20,20,0],"indexes":[0,1,2,2,1,3],"uv":[0,40,40,40,0,0,40,0],"nuv":[0,0,1,0,0,1,1,1],"minPos":{"x":-20,"y":-20,"z":0},"maxPos":{"x":20,"y":20,"z":0}},"packable":true,"pixelsToUnit":100,"pivot":{"x":0.5,"y":0.5},"meshType":0}],[0],0,[0],[7],[7]],[[[23,"PixelifySans-Regular","PixelifySans-Regular.ttf"],-1],0,0,[],[],[]],[[{"name":"mini_globulo_branco","rect":{"x":220,"y":225,"width":105,"height":105},"offset":{"x":22.5,"y":-27.5},"originalSize":{"width":500,"height":500},"rotated":false,"capInsets":[0,0,0,0],"vertices":{"rawPosition":[-52.5,-52.5,0,52.5,-52.5,0,-52.5,52.5,0,52.5,52.5,0],"indexes":[0,1,2,2,1,3],"uv":[220,275,325,275,220,170,325,170],"nuv":[0.44,0.34,0.65,0.34,0.44,0.55,0.65,0.55],"minPos":{"x":-52.5,"y":-52.5,"z":0},"maxPos":{"x":52.5,"y":52.5,"z":0}},"packable":true,"pixelsToUnit":100,"pivot":{"x":0.5,"y":0.5},"meshType":0}],[0],0,[0],[7],[8]],[[{"name":"mini_virus","rect":{"x":165,"y":175,"width":175,"height":175},"offset":{"x":2.5,"y":-12.5},"originalSize":{"width":500,"height":500},"rotated":false,"capInsets":[0,0,0,0],"vertices":{"rawPosition":[-87.5,-87.5,0,87.5,-87.5,0,-87.5,87.5,0,87.5,87.5,0],"indexes":[0,1,2,2,1,3],"uv":[165,325,340,325,165,150,340,150],"nuv":[0.33,0.3,0.68,0.3,0.33,0.65,0.68,0.65],"minPos":{"x":-87.5,"y":-87.5,"z":0},"maxPos":{"x":87.5,"y":87.5,"z":0}},"packable":true,"pixelsToUnit":100,"pivot":{"x":0.5,"y":0.5},"meshType":0}],[0],0,[0],[7],[9]],[[{"name":"default_btn_pressed","rect":{"x":0,"y":0,"width":40,"height":40},"offset":{"x":0,"y":0},"originalSize":{"width":40,"height":40},"rotated":false,"capInsets":[12,12,12,12],"vertices":{"rawPosition":[-20,-20,0,20,-20,0,-20,20,0,20,20,0],"indexes":[0,1,2,2,1,3],"uv":[0,40,40,40,0,0,40,0],"nuv":[0,0,1,0,0,1,1,1],"minPos":{"x":-20,"y":-20,"z":0},"maxPos":{"x":20,"y":20,"z":0}},"packable":true,"pixelsToUnit":100,"pivot":{"x":0.5,"y":0.5},"meshType":0}],[0],0,[0],[7],[10]],[[{"name":"computador","rect":{"x":145,"y":225,"width":250,"height":260},"offset":{"x":20,"y":-105},"originalSize":{"width":500,"height":500},"rotated":false,"capInsets":[0,0,0,0],"vertices":{"rawPosition":[-125,-130,0,125,-130,0,-125,130,0,125,130,0],"indexes":[0,1,2,2,1,3],"uv":[145,275,395,275,145,15,395,15],"nuv":[0.29,0.03,0.79,0.03,0.29,0.55,0.79,0.55],"minPos":{"x":-125,"y":-130,"z":0},"maxPos":{"x":125,"y":130,"z":0}},"packable":true,"pixelsToUnit":100,"pivot":{"x":0.5,"y":0.5},"meshType":0}],[0],0,[0],[7],[11]],[[{"name":"default_btn_disabled","rect":{"x":0,"y":0,"width":40,"height":40},"offset":{"x":0,"y":0},"originalSize":{"width":40,"height":40},"rotated":false,"capInsets":[12,12,12,12],"vertices":{"rawPosition":[-20,-20,0,20,-20,0,-20,20,0,20,20,0],"indexes":[0,1,2,2,1,3],"uv":[0,40,40,40,0,0,40,0],"nuv":[0,0,1,0,0,1,1,1],"minPos":{"x":-20,"y":-20,"z":0},"maxPos":{"x":20,"y":20,"z":0}},"packable":true,"pixelsToUnit":100,"pivot":{"x":0.5,"y":0.5},"meshType":0}],[0],0,[0],[7],[12]],[[{"name":"mini_globulo_vermelho","rect":{"x":60,"y":315,"width":85,"height":85},"offset":{"x":-147.5,"y":-107.5},"originalSize":{"width":500,"height":500},"rotated":false,"capInsets":[0,0,0,0],"vertices":{"rawPosition":[-42.5,-42.5,0,42.5,-42.5,0,-42.5,42.5,0,42.5,42.5,0],"indexes":[0,1,2,2,1,3],"uv":[60,185,145,185,60,100,145,100],"nuv":[0.12,0.2,0.29,0.2,0.12,0.37,0.29,0.37],"minPos":{"x":-42.5,"y":-42.5,"z":0},"maxPos":{"x":42.5,"y":42.5,"z":0}},"packable":true,"pixelsToUnit":100,"pivot":{"x":0.5,"y":0.5},"meshType":0}],[0],0,[0],[7],[13]],[[{"name":"board","rect":{"x":25,"y":115,"width":455,"height":120},"offset":{"x":2.5,"y":75},"originalSize":{"width":500,"height":500},"rotated":false,"capInsets":[0,0,0,0],"vertices":{"rawPosition":[-227.5,-60,0,227.5,-60,0,-227.5,60,0,227.5,60,0],"indexes":[0,1,2,2,1,3],"uv":[25,385,480,385,25,265,480,265],"nuv":[0.05,0.53,0.96,0.53,0.05,0.77,0.96,0.77],"minPos":{"x":-227.5,"y":-60,"z":0},"maxPos":{"x":227.5,"y":60,"z":0}},"packable":true,"pixelsToUnit":100,"pivot":{"x":0.5,"y":0.5},"meshType":0}],[0],0,[0],[7],[14]],[[{"name":"options","rect":{"x":462,"y":27,"width":133,"height":65},"offset":{"x":28.5,"y":-9.5},"originalSize":{"width":1000,"height":100},"rotated":false,"capInsets":[0,0,0,0],"vertices":{"rawPosition":[-66.5,-32.5,0,66.5,-32.5,0,-66.5,32.5,0,66.5,32.5,0],"indexes":[0,1,2,2,1,3],"uv":[462,73,595,73,462,8,595,8],"nuv":[0.462,0.08,0.595,0.08,0.462,0.73,0.595,0.73],"minPos":{"x":-66.5,"y":-32.5,"z":0},"maxPos":{"x":66.5,"y":32.5,"z":0}},"packable":true,"pixelsToUnit":100,"pivot":{"x":0.5,"y":0.5},"meshType":0}],[0],0,[0],[7],[15]],[[[24,"SceneGame"],[16,"WBC",1,[-3,-4,-5,-6,-7],[[[0,-1,[5,325.478,130.42589099573115]],-2],4,1],[1,-1.0950000000000273,24.19150000000002,0]],[16,"Virus",1,[-10,-11,-12,-13,-14],[[[0,-8,[5,325.478,130.42589099573115]],-9],4,1],[1,1.8239999999998417,25.650499999999965,0]],[16,"RBC",1,[-17,-18,-19,-20],[[[0,-15,[5,325.478,130.42589099573115]],-16],4,1],[1,1.8239999999998417,25.650499999999965,0]],[27,"Canvas",33554432,"f8rZ82BKlA757fpsJaOTg9",[-26,-27,-28,-29,-30,-31],[[32,-22,-21],[33,45,-23],[10,-24],[0,-25,[5,1280,720]]],[1,640,360,0]],[1,"PopUpWindow",1,4,[-36,-37,-38],[[13,0,-32,128,129],[35,-33],[10,-34],[2,-35,[5,364,234],[0,0.7551042164769209,0.8166841919652545]]],[1,479.878,277.374,0]],[17,"PopulationBoard",33554432,4,[-42,-43,-44,-45,-46,-47],[[[0,-39,[5,586.463,90.485]],[14,0,-40,133],-41],4,4,1],[1,-312.4515,288.5305,0]],[1,"DropDown",1,5,[-55,-56],[[34,0,-48,123],[10,-49],[2,-50,[5,250.8,110.2],[0,1.913377237978395,1.2607700770995907]],[36,-54,-53,-52,-51]],[1,220.1,19.7,0]],[17,"WindowContent",1,5,[1,3,2,-59],[[[0,-57,[5,327.464,159.619]],-58],4,1],[1,-93.00399999999999,-92.2675,0]],[1,"Options",1,7,[-63,-64],[[13,0,-60,119,120],[10,-61],[2,-62,[5,251.6,73.017],[0,1.3522284844232177,1.0863846324727264]]],[1,-138.26,-20.576000000000022,-1000]],[1,"SelectedOption",1,7,[-70],[[13,0,-65,121,122],[20,-67,[[15,"4de6e3gLBhEEJi/mQFx37BW","toggleDropdown",7]],[4,4294967295],[4,4292072403],-66],[10,-68],[2,-69,[5,252,29.4],[0,1.2979664002350204,-2.1644819351543583]]],[1,-151.676,-84.212,-1000]],[28,"Computer",512,1,4,[[13,0,-71,1,2],[20,-73,[[15,"ff3228rtPpJRYYqQzVqs25b","Show_Window",5]],[4,4294967295],[4,4292072403],-72],[10,-74],[2,-75,[5,99,103],[0,0.532385547383333,0.7739656306174938]]],[1,568.878,323.006,0]],[1,"option1",1,9,[-80],[[0,-76,[5,244.017,29.516000000000005]],[19,1,0,-77],[21,2,-79,[4,4292269782],-78]],[1,-214.68050000000002,-25.018,0]],[1,"option2",1,9,[-85],[[0,-81,[5,244.017,29.516000000000005]],[19,1,0,-82],[21,2,-84,[4,4292269782],-83]],[1,-214.6809999999998,-59.27600000000007,0]],[11,"Healt",1,1,[-87,-88,-89],[[8,-86]]],[1,"add",1,14,[-93],[[0,-90,[5,20.541,20.714999999999996]],[4,2,-92,[[5,"e1d48uE7jtHQpbucvyrJ7nN","addPoint","healthValue",1]],[4,4292269782],-91,3,4,5,6]],[1,81.52199999999993,47.572,0]],[1,"remove",1,14,[-97],[[2,-94,[5,19.091,16.072999999999997],[0,0.5,0.7526597399365396]],[4,2,-96,[[5,"e1d48uE7jtHQpbucvyrJ7nN","removePoint","healthValue",1]],[4,4292269782],-95,7,8,9,10]],[1,59.184999999999945,50.75300000000004,0]],[11,"Speed",1,1,[-99,-100,-101],[[8,-98]]],[1,"add",1,17,[-105],[[0,-102,[5,20.541,20.714999999999996]],[4,2,-104,[[5,"e1d48uE7jtHQpbucvyrJ7nN","addPoint","speedValue",1]],[4,4292269782],-103,11,12,13,14]],[1,81.92699999999991,24.489000000000033,0]],[1,"remove",1,17,[-109],[[2,-106,[5,19.091,16.072999999999997],[0,0.5,0.7526597399365396]],[4,2,-108,[[5,"e1d48uE7jtHQpbucvyrJ7nN","removePoint","speedValue",1]],[4,4292269782],-107,15,16,17,18]],[1,59.58999999999992,29.63900000000001,0]],[11,"Strength",1,1,[-111,-112,-113],[[8,-110]]],[1,"add",1,20,[-117],[[0,-114,[5,20.541,20.714999999999996]],[4,2,-116,[[5,"e1d48uE7jtHQpbucvyrJ7nN","addPoint","strengthValue",1]],[4,4292269782],-115,19,20,21,22]],[1,81.98800000000006,2.38900000000001,0]],[1,"remove",1,20,[-121],[[2,-118,[5,19.091,16.072999999999997],[0,0.5,0.7526597399365396]],[4,2,-120,[[5,"e1d48uE7jtHQpbucvyrJ7nN","removePoint","strengthValue",1]],[4,4292269782],-119,23,24,25,26]],[1,60.14899999999989,4.56899999999996,0]],[11,"Resistance",1,1,[-123,-124,-125],[[8,-122]]],[1,"remove",1,23,[-129],[[2,-126,[5,19.091,16.072999999999997],[0,0.5,0.7526597399365396]],[4,2,-128,[[5,"e1d48uE7jtHQpbucvyrJ7nN","removePoint","resistanceValue",1]],[4,4292269782],-127,27,28,29,30]],[1,61.02800000000002,-19.173999999999978,0]],[1,"add",1,23,[-133],[[0,-130,[5,20.541,20.714999999999996]],[4,2,-132,[[5,"e1d48uE7jtHQpbucvyrJ7nN","addPoint","resistanceValue",1]],[4,4292269782],-131,31,32,33,34]],[1,82.86699999999996,-22.94399999999996,0]],[11,"ReproductionRate",1,1,[-135,-136,-137],[[8,-134]]],[1,"remove",1,26,[-141],[[2,-138,[5,19.091,16.072999999999997],[0,0.5,0.7526597399365396]],[4,2,-140,[[5,"e1d48uE7jtHQpbucvyrJ7nN","removePoint","reproductionRateValue",1]],[4,4292269782],-139,35,36,37,38]],[1,61.468000000000075,-42.60699999999997,0]],[1,"add",1,26,[-145],[[0,-142,[5,20.541,20.714999999999996]],[4,2,-144,[[5,"e1d48uE7jtHQpbucvyrJ7nN","addPoint","reproductionRateValue",1]],[4,4292269782],-143,39,40,41,42]],[1,83.30700000000002,-45.807000000000016,0]],[11,"Health",1,3,[-147,-148,-149],[[8,-146]]],[1,"add",1,29,[-153],[[0,-150,[5,20.541,20.714999999999996]],[4,2,-152,[[5,"cc9a2OcZ7BH4oet9K5jsA5d","addPoint","healthValue",3]],[4,4292269782],-151,43,44,45,46]],[1,78.7610000000002,45.506000000000085,0]],[1,"remove",1,29,[-157],[[2,-154,[5,19.091,16.072999999999997],[0,0.5,0.7526597399365396]],[4,2,-156,[[5,"cc9a2OcZ7BH4oet9K5jsA5d","removePoint","healthValue",3]],[4,4292269782],-155,47,48,49,50]],[1,56.424000000000206,50,0]],[11,"Speed",1,3,[-159,-160,-161],[[8,-158]]],[1,"remove",1,32,[-165],[[2,-162,[5,19.091,16.072999999999997],[0,0.5,0.7526597399365396]],[4,2,-164,[[5,"cc9a2OcZ7BH4oet9K5jsA5d","removePoint","speedValue",3]],[4,4292269782],-163,51,52,53,54]],[1,56.83200000000011,27.28200000000004,0]],[1,"add",1,32,[-169],[[0,-166,[5,20.541,20.714999999999996]],[4,2,-168,[[5,"cc9a2OcZ7BH4oet9K5jsA5d","addPoint","speedValue",3]],[4,4292269782],-167,55,56,57,58]],[1,79.1690000000001,23.74700000000007,0]],[11,"Resistance",1,3,[-171,-172,-173],[[8,-170]]],[1,"add",1,35,[-177],[[0,-174,[5,20.541,20.714999999999996]],[4,2,-176,[[5,"cc9a2OcZ7BH4oet9K5jsA5d","addPoint","resistanceValue",3]],[4,4292269782],-175,59,60,61,62]],[1,79.1690000000001,0.03700000000003456,0]],[1,"remove",1,35,[-181],[[2,-178,[5,19.091,16.072999999999997],[0,0.5,0.7526597399365396]],[4,2,-180,[[5,"cc9a2OcZ7BH4oet9K5jsA5d","removePoint","resistanceValue",3]],[4,4292269782],-179,63,64,65,66]],[1,56.83200000000011,3.5720000000000027,0]],[1,"ReproductionRate",1,3,[-183,-184,-185],[[8,-182]],[1,-1.8239999999998417,-25.650499999999965,0]],[1,"remove",1,38,[-189],[[2,-186,[5,19.091,16.072999999999997],[0,0.5,0.7526597399365396]],[4,2,-188,[[5,"cc9a2OcZ7BH4oet9K5jsA5d","removePoint","reproductionRateValue",3]],[4,4292269782],-187,67,68,69,70]],[1,59.801,4.745,0]],[1,"add",1,38,[-193],[[0,-190,[5,20.541,20.714999999999996]],[4,2,-192,[[5,"cc9a2OcZ7BH4oet9K5jsA5d","addPoint","reproductionRateValue",3]],[4,4292269782],-191,71,72,73,74]],[1,81.64,0.971,0]],[1,"Health",1,2,[-195,-196,-197],[[8,-194]],[1,-1.824,-0.846,0]],[1,"add",1,41,[-201],[[0,-198,[5,20.541,20.714999999999996]],[4,2,-200,[[5,"6da4fGUOd5IzZ8j4KlDjm2X","addPoint","healthValue",2]],[4,4292269782],-199,75,76,77,78]],[1,81.52199999999993,47.572,0]],[1,"remove",1,41,[-205],[[2,-202,[5,19.091,16.072999999999997],[0,0.5,0.7526597399365396]],[4,2,-204,[[5,"6da4fGUOd5IzZ8j4KlDjm2X","removePoint","healthValue",2]],[4,4292269782],-203,79,80,81,82]],[1,59.184999999999945,50.75300000000004,0]],[1,"Speed",1,2,[-207,-208,-209],[[8,-206]],[1,-1.8240000000000691,-0.8460000000000036,0]],[1,"add",1,44,[-213],[[0,-210,[5,20.541,20.714999999999996]],[4,2,-212,[[5,"6da4fGUOd5IzZ8j4KlDjm2X","addPoint","speedValue",2]],[4,4292269782],-211,83,84,85,86]],[1,81.92699999999991,24.489000000000033,0]],[1,"remove",1,44,[-217],[[2,-214,[5,19.091,16.072999999999997],[0,0.5,0.7526597399365396]],[4,2,-216,[[5,"6da4fGUOd5IzZ8j4KlDjm2X","removePoint","speedValue",2]],[4,4292269782],-215,87,88,89,90]],[1,59.58999999999992,29.63900000000001,0]],[1,"Strength",1,2,[-219,-220,-221],[[8,-218]],[1,-1.8239999999998417,-25.650499999999965,0]],[1,"add",1,47,[-225],[[0,-222,[5,20.541,20.714999999999996]],[4,2,-224,[[5,"6da4fGUOd5IzZ8j4KlDjm2X","addPoint","strengthValue",2]],[4,4292269782],-223,91,92,93,94]],[1,81.988,25.08,0]],[1,"remove",1,47,[-229],[[2,-226,[5,19.091,16.072999999999997],[0,0.5,0.7526597399365396]],[4,2,-228,[[5,"6da4fGUOd5IzZ8j4KlDjm2X","removePoint","strengthValue",2]],[4,4292269782],-227,95,96,97,98]],[1,60.149,27.26,0]],[1,"Resistance",1,2,[-231,-232,-233],[[8,-230]],[1,-1.824,-0.846,0]],[1,"remove",1,50,[-237],[[2,-234,[5,19.091,16.072999999999997],[0,0.5,0.7526597399365396]],[4,2,-236,[[5,"6da4fGUOd5IzZ8j4KlDjm2X","removePoint","resistanceValue",2]],[4,4292269782],-235,99,100,101,102]],[1,61.02800000000002,-19.173999999999978,0]],[1,"add",1,50,[-241],[[0,-238,[5,20.541,20.714999999999996]],[4,2,-240,[[5,"6da4fGUOd5IzZ8j4KlDjm2X","addPoint","resistanceValue",2]],[4,4292269782],-239,103,104,105,106]],[1,82.86699999999996,-22.94399999999996,0]],[1,"ReproductionRate",1,2,[-243,-244,-245],[[8,-242]],[1,-1.824,-0.846,0]],[1,"remove",1,53,[-249],[[2,-246,[5,19.091,16.072999999999997],[0,0.5,0.7526597399365396]],[4,2,-248,[[5,"6da4fGUOd5IzZ8j4KlDjm2X","removePoint","reproductionRateValue",2]],[4,4292269782],-247,107,108,109,110]],[1,61.468000000000075,-42.60699999999997,0]],[1,"add",1,53,[-253],[[0,-250,[5,20.541,20.714999999999996]],[4,2,-252,[[5,"6da4fGUOd5IzZ8j4KlDjm2X","addPoint","reproductionRateValue",2]],[4,4292269782],-251,111,112,113,114]],[1,83.30700000000002,-45.807000000000016,0]],[12,"CloseWindowButton",1,5,[[37,2,-255,[[15,"ff3228rtPpJRYYqQzVqs25b","Hide_Window",5],[15,"4de6e3gLBhEEJi/mQFx37BW","closeDropdown",7]],[4,4293322470],[4,4294967295],[4,4291348680],[4,3363338360],-254,124,125,126,127],[10,-256],[0,-257,[5,35.1,30.3]]],[1,53.178,15.279,-1000]],[29,"TiledMap",512,33554432,4,[-260],[[0,-258,[5,1280,736]],[38,-259,0]]],[25,"Main Camera",512,1,4,[[-261,[10,-262],[0,-263,[5,0,0]]],1,4,4],[1,0,0,1000]],[39],[17,"Points",1,8,[-265],[[[0,-264,[5,153.386,36.099]],59],4,1],[1,93.01999999999997,-71.513,0]],[12,"Label",1,12,[[22,"glóbulo branco",0,20,20,1,false,false,0,1,-266,[4,4291809231],115,116],[10,-267],[2,-268,[5,240.15699999999998,28.5],[0,4.717563882500722,1.8700502541002997]]],[1,1014.8075,39.55476308488426,0]],[12,"Label",1,13,[[22,"vírus",0,20,20,1,false,false,0,1,-269,[4,4291809231],117,118],[10,-270],[2,-271,[5,228.736,29],[0,-6.7058992797924075,-30.96540716945384]]],[1,-1650.111,-907.497,0]],[42,"SceneGame",[4,-272],[43,null,null,"e3a98571-c8eb-4350-a5a4-4992bc0b5f9b",null,null,null],[44,[45,0.78125,[2,0.2,0.5019607843137255,0.8,0.520833125],[2,0.2,0.5019607843137255,0.8,0.520833125]],[46,[0,512,512]],[47],[48,[4,4292993505]],[49],[50],[51],[52]]],[30,"Camada de Tiles 1",512,33554432,57,[[0,-273,[5,1280,736]],[53,-274]]],[7,"Label",1,14,[[[2,-275,[5,44.05995178222656,50.4],[0,0.016469424543563704,0.5]],-276],4,1],[1,-160.9000000000001,43.894054502134395,0]],[3,"Label",33554432,15,[[0,-277,[5,100,40]],[6,"+",39.7,39.7,1,false,-278,[4,4278236232]]]],[3,"Label",33554432,16,[[0,-279,[5,100,40]],[6,"-",39.7,39.7,1,false,-280,[4,4278190330]]]],[7,"Label",1,17,[[[2,-281,[5,44.05995178222656,50.4],[0,-0.000782620753408847,0.5]],-282],4,1],[1,-161.99400000000003,21.162054502134424,0]],[3,"Label",33554432,18,[[0,-283,[5,100,40]],[6,"+",39.7,39.7,1,false,-284,[4,4278236232]]]],[3,"Label",33554432,19,[[0,-285,[5,100,40]],[6,"-",39.7,39.7,1,false,-286,[4,4278190330]]]],[7,"Label",1,20,[[[2,-287,[5,44.05995178222656,50.4],[0,-0.000782620753408847,0.485515873015873]],-288],4,1],[1,-161.99400000000003,-2.9179454978656167,0]],[3,"Label",33554432,21,[[0,-289,[5,100,40]],[6,"+",39.7,39.7,1,false,-290,[4,4278236232]]]],[3,"Label",33554432,22,[[0,-291,[5,100,40]],[6,"-",39.7,39.7,1,false,-292,[4,4278190330]]]],[7,"Label",1,23,[[[2,-293,[5,44.05995178222656,50.4],[0,-0.01805833140744162,0.5]],-294],4,1],[1,-163.1210000000001,-25.2119454978656,0]],[3,"Label",33554432,24,[[0,-295,[5,100,40]],[6,"-",39.7,39.7,1,false,-296,[4,4278190330]]]],[3,"Label",33554432,25,[[0,-297,[5,100,40]],[6,"+",39.7,39.7,1,false,-298,[4,4278236232]]]],[7,"Label",1,26,[[[2,-299,[5,44.05995178222656,50.4],[0,-0.0008062861104691128,0.49999999999999994]],-300],4,1],[1,-162.39200000000005,-47.8369454978656,0]],[3,"Label",33554432,27,[[0,-301,[5,100,40]],[6,"-",39.7,39.7,1,false,-302,[4,4278190330]]]],[3,"Label",33554432,28,[[0,-303,[5,100,40]],[6,"+",39.7,39.7,1,false,-304,[4,4278236232]]]],[7,"Label",1,60,[[[2,-305,[5,44.05995178222656,50.4],[0,0.9789158308296741,0.5]],-306],4,1],[1,65.6690000000001,-0.4634999999999536,0]],[7,"Label",1,29,[[[2,-307,[5,44.05995178222656,50.4],[0,0.016469424543563704,0.5]],-308],4,1],[1,-160.2030000000001,43.56094549786553,0]],[3,"Label",33554432,30,[[0,-309,[5,100,40]],[6,"+",39.7,39.7,1,false,-310,[4,4278236232]]]],[3,"Label",33554432,31,[[0,-311,[5,100,40]],[6,"-",39.7,39.7,1,false,-312,[4,4278190330]]]],[7,"Label",1,32,[[[2,-313,[5,44.05995178222656,50.4],[0,0.016469424543563704,0.5]],-314],4,1],[1,-159.838,19.562,0]],[3,"Label",33554432,33,[[0,-315,[5,100,40]],[6,"-",39.7,39.7,1,false,-316,[4,4278190330]]]],[3,"Label",33554432,34,[[0,-317,[5,100,40]],[6,"+",39.7,39.7,1,false,-318,[4,4278236232]]]],[7,"Label",1,35,[[[2,-319,[5,44.05995178222656,50.4],[0,0.016469424543563704,0.5144841269841269]],-320],4,1],[1,-160.9,-2.858,0]],[3,"Label",33554432,36,[[0,-321,[5,100,40]],[6,"+",39.7,39.7,1,false,-322,[4,4278236232]]]],[3,"Label",33554432,37,[[0,-323,[5,100,40]],[6,"-",39.7,39.7,1,false,-324,[4,4278190330]]]],[7,"Label",1,38,[[[2,-325,[5,44.05995178222656,50.4],[0,-0.01805833140744162,0.5]],-326],4,1],[1,-163.121,-1.295,0]],[3,"Label",33554432,39,[[0,-327,[5,100,40]],[6,"-",39.7,39.7,1,false,-328,[4,4278190330]]]],[3,"Label",33554432,40,[[0,-329,[5,100,40]],[6,"+",39.7,39.7,1,false,-330,[4,4278236232]]]],[7,"Label",1,41,[[[2,-331,[5,44.05995178222656,50.4],[0,0.016469424543563704,0.5]],-332],4,1],[1,-160.9000000000001,43.894054502134395,0]],[3,"Label",33554432,42,[[0,-333,[5,100,40]],[6,"+",39.7,39.7,1,false,-334,[4,4278236232]]]],[3,"Label",33554432,43,[[0,-335,[5,100,40]],[6,"-",39.7,39.7,1,false,-336,[4,4278190330]]]],[7,"Label",1,44,[[[2,-337,[5,44.05995178222656,50.4],[0,-0.000782620753408847,0.5]],-338],4,1],[1,-161.99400000000003,21.162054502134424,0]],[3,"Label",33554432,45,[[0,-339,[5,100,40]],[6,"+",39.7,39.7,1,false,-340,[4,4278236232]]]],[3,"Label",33554432,46,[[0,-341,[5,100,40]],[6,"-",39.7,39.7,1,false,-342,[4,4278190330]]]],[7,"Label",1,47,[[[2,-343,[5,44.05995178222656,50.4],[0,-0.000782620753408847,0.485515873015873]],-344],4,1],[1,-161.994,19.773,0]],[3,"Label",33554432,48,[[0,-345,[5,100,40]],[6,"+",39.7,39.7,1,false,-346,[4,4278236232]]]],[3,"Label",33554432,49,[[0,-347,[5,100,40]],[6,"-",39.7,39.7,1,false,-348,[4,4278190330]]]],[7,"Label",1,50,[[[2,-349,[5,44.05995178222656,50.4],[0,-0.01805833140744162,0.5]],-350],4,1],[1,-163.1210000000001,-25.2119454978656,0]],[3,"Label",33554432,51,[[0,-351,[5,100,40]],[6,"-",39.7,39.7,1,false,-352,[4,4278190330]]]],[3,"Label",33554432,52,[[0,-353,[5,100,40]],[6,"+",39.7,39.7,1,false,-354,[4,4278236232]]]],[7,"Label",1,53,[[[2,-355,[5,44.05995178222656,50.4],[0,-0.0008062861104691128,0.49999999999999994]],-356],4,1],[1,-162.39200000000005,-47.8369454978656,0]],[3,"Label",33554432,54,[[0,-357,[5,100,40]],[6,"-",39.7,39.7,1,false,-358,[4,4278190330]]]],[3,"Label",33554432,55,[[0,-359,[5,100,40]],[6,"+",39.7,39.7,1,false,-360,[4,4278236232]]]],[7,"Label",1,10,[[[0,-361,[5,158.57981872558594,50.4]],-362],4,1],[1,-215.44299999999998,80.14499999999987,0]],[26,"Spawner",33554432,4,[[[8,-363],-364],4,1]],[12,"Wbc",33554432,6,[[0,-365,[5,37.443999999999996,37.443999999999996]],[14,0,-366,130]],[1,-70.212,0.236,0]],[12,"Virus",33554432,6,[[0,-367,[5,56.653999999999996,56.653999999999996]],[14,0,-368,131]],[1,109.728,0.236,0]],[12,"Rbc",33554432,6,[[0,-369,[5,31.409,31.409]],[14,0,-370,132]],[1,-252.9905,0.23649999999997817,0]],[7,"RbcCount",33554432,6,[[[2,-371,[5,23.439987182617188,50.4],[0,-0.008873998397305516,0.5083134920634921]],-372],4,1],[1,-227.803,1.4569999999999936,0]],[7,"WbcCount",33554432,6,[[[2,-373,[5,23.439987182617188,50.4],[0,0.004649899782770417,0.5]],-374],4,1],[1,-40.617999999999995,3.0750000000000455,0]],[7,"VirusCount",33554432,6,[[[2,-375,[5,23.439987182617188,50.4],[0,0.007593587399253865,0.5]],-376],4,1],[1,145.11100000000005,3.0750000000000455,0]],[31,"GameCtrl","37926xts9J2KAxiUFGPl0p",63,[[0,-377,[5,1280,720]],[54,-379,-378]],[1,640.932,359.441,0]],[55,0,-1,60,611.8321392016377,4096,4294967295,58,[4,4278190080]],[9,0,20,20,false,65],[9,0,20,20,false,68],[9,0,20,20,false,71],[9,0,20,20,false,74],[9,0,20,20,false,77],[56,1,118,119,120,121,122,59],[40,2,20,20,false,80,[4,4282565136]],[9,0,20,20,false,81],[9,0,20,20,false,84],[9,0,20,20,false,87],[9,0,20,20,false,90],[57,3,125,126,127,128,59],[9,0,20,20,false,93],[9,0,20,20,false,96],[9,0,20,20,false,99],[9,0,20,20,false,102],[9,0,20,20,false,105],[58,2,130,131,132,133,134,59],[59,8,2,1,3],[41,"glóbulo vermelho",0,20,20,false,108,[4,4282565136]],[60,109,135,129,123],[61,6],[18,"0",0,40,false,113,[4,4282565136]],[18,"0",0,40,false,114,[4,4282565136]],[18,"0",0,40,false,115,[4,4282565136]]],0,[0,0,1,0,-2,123,0,-1,14,0,-2,17,0,-3,20,0,-4,23,0,-5,26,0,0,2,0,-2,135,0,-1,41,0,-2,44,0,-3,47,0,-4,50,0,-5,53,0,0,3,0,-2,129,0,-1,29,0,-2,32,0,-3,35,0,-4,38,0,11,117,0,0,4,0,0,4,0,0,4,0,0,4,0,-1,57,0,-2,58,0,-3,11,0,-4,5,0,-5,109,0,-6,6,0,0,5,0,0,5,0,0,5,0,0,5,0,-1,8,0,-2,7,0,-3,56,0,0,6,0,0,6,0,-3,139,0,-1,110,0,-2,111,0,-3,112,0,-4,113,0,-5,114,0,-6,115,0,0,7,0,0,7,0,0,7,0,12,136,0,13,9,0,14,137,0,0,7,0,-1,9,0,-2,10,0,0,8,0,-2,136,0,-4,60,0,0,9,0,0,9,0,0,9,0,-1,12,0,-2,13,0,0,10,0,1,10,0,0,10,0,0,10,0,0,10,0,-1,108,0,0,11,0,1,11,0,0,11,0,0,11,0,0,11,0,0,12,0,0,12,0,1,12,0,0,12,0,-1,61,0,0,13,0,0,13,0,1,13,0,0,13,0,-1,62,0,0,14,0,-1,65,0,-2,15,0,-3,16,0,0,15,0,1,15,0,0,15,0,-1,66,0,0,16,0,1,16,0,0,16,0,-1,67,0,0,17,0,-1,68,0,-2,18,0,-3,19,0,0,18,0,1,18,0,0,18,0,-1,69,0,0,19,0,1,19,0,0,19,0,-1,70,0,0,20,0,-1,71,0,-2,21,0,-3,22,0,0,21,0,1,21,0,0,21,0,-1,72,0,0,22,0,1,22,0,0,22,0,-1,73,0,0,23,0,-1,74,0,-2,24,0,-3,25,0,0,24,0,1,24,0,0,24,0,-1,75,0,0,25,0,1,25,0,0,25,0,-1,76,0,0,26,0,-1,77,0,-2,27,0,-3,28,0,0,27,0,1,27,0,0,27,0,-1,78,0,0,28,0,1,28,0,0,28,0,-1,79,0,0,29,0,-1,81,0,-2,30,0,-3,31,0,0,30,0,1,30,0,0,30,0,-1,82,0,0,31,0,1,31,0,0,31,0,-1,83,0,0,32,0,-1,84,0,-2,33,0,-3,34,0,0,33,0,1,33,0,0,33,0,-1,85,0,0,34,0,1,34,0,0,34,0,-1,86,0,0,35,0,-1,87,0,-2,36,0,-3,37,0,0,36,0,1,36,0,0,36,0,-1,88,0,0,37,0,1,37,0,0,37,0,-1,89,0,0,38,0,-1,90,0,-2,39,0,-3,40,0,0,39,0,1,39,0,0,39,0,-1,91,0,0,40,0,1,40,0,0,40,0,-1,92,0,0,41,0,-1,93,0,-2,42,0,-3,43,0,0,42,0,1,42,0,0,42,0,-1,94,0,0,43,0,1,43,0,0,43,0,-1,95,0,0,44,0,-1,96,0,-2,45,0,-3,46,0,0,45,0,1,45,0,0,45,0,-1,97,0,0,46,0,1,46,0,0,46,0,-1,98,0,0,47,0,-1,99,0,-2,48,0,-3,49,0,0,48,0,1,48,0,0,48,0,-1,100,0,0,49,0,1,49,0,0,49,0,-1,101,0,0,50,0,-1,102,0,-2,51,0,-3,52,0,0,51,0,1,51,0,0,51,0,-1,103,0,0,52,0,1,52,0,0,52,0,-1,104,0,0,53,0,-1,105,0,-2,54,0,-3,55,0,0,54,0,1,54,0,0,54,0,-1,106,0,0,55,0,1,55,0,0,55,0,-1,107,0,1,56,0,0,56,0,0,56,0,0,56,0,0,57,0,0,57,0,-1,64,0,-1,117,0,0,58,0,0,58,0,0,60,0,-1,80,0,0,61,0,0,61,0,0,61,0,0,62,0,0,62,0,0,62,0,-2,116,0,0,64,0,0,64,0,0,65,0,-2,118,0,0,66,0,0,66,0,0,67,0,0,67,0,0,68,0,-2,119,0,0,69,0,0,69,0,0,70,0,0,70,0,0,71,0,-2,120,0,0,72,0,0,72,0,0,73,0,0,73,0,0,74,0,-2,121,0,0,75,0,0,75,0,0,76,0,0,76,0,0,77,0,-2,122,0,0,78,0,0,78,0,0,79,0,0,79,0,0,80,0,-2,124,0,0,81,0,-2,125,0,0,82,0,0,82,0,0,83,0,0,83,0,0,84,0,-2,126,0,0,85,0,0,85,0,0,86,0,0,86,0,0,87,0,-2,127,0,0,88,0,0,88,0,0,89,0,0,89,0,0,90,0,-2,128,0,0,91,0,0,91,0,0,92,0,0,92,0,0,93,0,-2,130,0,0,94,0,0,94,0,0,95,0,0,95,0,0,96,0,-2,131,0,0,97,0,0,97,0,0,98,0,0,98,0,0,99,0,-2,132,0,0,100,0,0,100,0,0,101,0,0,101,0,0,102,0,-2,133,0,0,103,0,0,103,0,0,104,0,0,104,0,0,105,0,-2,134,0,0,106,0,0,106,0,0,107,0,0,107,0,0,108,0,-2,137,0,0,109,0,-2,138,0,0,110,0,0,110,0,0,111,0,0,111,0,0,112,0,0,112,0,0,113,0,-2,140,0,0,114,0,-2,141,0,0,115,0,-2,142,0,0,116,0,15,138,0,0,116,0,16,63,1,10,8,2,10,8,3,10,8,4,10,63,59,17,124,59,0,60,138,18,139,139,19,141,139,20,140,139,21,142,379],[0,0,0,0,0,0,0,0,0,0,0,0,0,0,0,0,0,0,0,0,0,0,0,0,0,0,0,0,0,0,0,0,0,0,0,0,0,0,0,0,0,0,0,0,0,0,0,0,0,0,0,0,0,0,0,0,0,0,0,0,0,0,0,0,0,0,0,0,0,0,0,0,0,0,0,0,0,0,0,0,0,0,0,0,0,0,0,0,0,0,0,0,0,0,0,0,0,0,0,0,0,0,0,0,0,0,0,0,0,0,0,0,0,0,0,0,0,0,0,0,0,0,0,0,0,0,0,0,0,0,0,0,0,0,118,119,120,121,122,124,125,126,127,128,130,131,132,133,134,137,138,138,138,140,141,142],[22,9,8,2,3,4,5,2,3,4,5,2,3,4,5,2,3,4,5,2,3,4,5,2,3,4,5,2,3,4,5,2,3,4,5,2,3,4,5,2,3,4,5,2,3,4,5,2,3,4,5,2,3,4,5,2,3,4,5,2,3,4,5,2,3,4,5,2,3,4,5,2,3,4,5,2,3,4,5,2,3,4,5,2,3,4,5,2,3,4,5,2,3,4,5,2,3,4,5,2,3,4,5,2,3,4,5,2,3,4,5,2,3,4,5,9,6,9,6,9,8,9,8,9,2,3,4,5,9,8,8,8,8,8,6,6,6,6,6,6,6,6,6,6,6,6,6,6,6,6,23,24,25,6,6,6],[16,4,17,0,0,1,2,0,0,1,2,0,0,1,2,0,0,1,2,0,0,1,2,0,0,1,2,0,0,1,2,0,0,1,2,0,0,1,2,0,0,1,2,0,0,1,2,0,0,1,2,0,0,1,2,0,0,1,2,0,0,1,2,0,0,1,2,0,0,1,2,0,0,1,2,0,0,1,2,0,0,1,2,0,0,1,2,0,0,1,2,0,0,1,2,0,0,1,2,0,0,1,2,0,0,1,2,0,0,1,2,0,0,1,2,4,3,4,3,4,18,4,19,4,0,0,1,2,4,20,21,22,23,24,3,3,3,3,3,3,3,3,3,3,3,3,3,3,3,3,25,26,27,3,3,3]]]]
